{
	"Meta":	{
		"Name":	"example level",
		"Comment":	"",
		"Width":	256,
		"Height":	15,
		"TileWidth":	16,
		"TileHeight":	16,
		"GridWidth":	16,
		"GridHeight":	15,
		"ExportFormat":	"PrincessNES",
		"FormatVersion":	1
	},
	"Config":	{
		"StartDialog":	"MeetKeeAgain"
	},
	"Header":	{
		"Music":	"WORLD_5",
		"SpriteGFX":	["SP_HANNAH", "SP_EXPLODE", "SP_CASTLE", "SP_WIND"],
		"GFXUpload":	["PAL_DABG_GRAY2", "PAL_ENEMY7", "BG_DABGCOMMON", "BG_DABG", "BG_HANNAH", "BG_JUNGLE"],
		"BGColor":	49
	},
	"Layers":	[{
			"Name":	"Foreground",
			"Type":	"Rectangle",
			"Tileset":	"novafg",
			"Data":	[{
					"Id":	"GROUND",
					"X":	0,
					"Y":	13,
					"W":	22,
					"H":	2
				}, {
					"Id":	"GROUND",
					"X":	16,
					"Y":	11,
					"W":	6,
					"H":	2
				}, {
					"Id":	"WOOD_PLATFORM",
					"X":	5,
					"Y":	7,
					"W":	1,
					"H":	6
				}, {
					"Id":	"SQUIRREL_BUSH",
					"X":	3,
					"Y":	5,
					"W":	5,
					"H":	2
				}, {
					"Id":	"SQUIRREL_BUSH",
					"X":	4,
					"Y":	4,
					"W":	3,
					"H":	1
				}, {
					"Id":	"WOOD_CRATE",
					"X":	17,
					"Y":	9,
					"W":	1,
					"H":	1
				}, {
					"Id":	"WOOD_PLATFORM",
					"X":	9,
					"Y":	9,
					"W":	1,
					"H":	4
				}, {
					"Id":	"SQUIRREL_BUSH",
					"X":	8,
					"Y":	7,
					"W":	3,
					"H":	2
				}, {
					"Id":	"SQUIRREL_BUSH",
					"X":	9,
					"Y":	6,
					"W":	1,
					"H":	1
				}, {
					"Id":	"SQUIRREL_BUSH",
					"X":	9,
					"Y":	3,
					"W":	5,
					"H":	2
				}, {
					"Id":	"WOOD_PLATFORM",
					"X":	11,
					"Y":	5,
					"W":	1,
					"H":	8
				}, {
					"Id":	"SQUIRREL_BUSH",
					"X":	10,
					"Y":	2,
					"W":	3,
					"H":	1
				}, {
					"Id":	"BIG_SPIKY_BUSH",
					"X":	6,
					"Y":	12,
					"W":	1,
					"H":	1
				}, {
					"Id":	"PALM_TREE",
					"X":	3,
					"Y":	9,
					"W":	1,
					"H":	4
				}, {
					"Id":	"PALM_TREE",
					"X":	12,
					"Y":	9,
					"W":	1,
					"H":	4
				}, {
					"Id":	"SQUIRREL_BUSH",
					"X":	23,
					"Y":	9,
					"W":	3,
					"H":	2
				}, {
					"Id":	"SQUIRREL_BUSH",
					"X":	27,
					"Y":	11,
					"W":	3,
					"H":	2
				}, {
					"Id":	"SQUIRREL_BUSH",
					"X":	31,
					"Y":	10,
					"W":	3,
					"H":	2
				}, {
					"Id":	"WOOD_PLATFORM",
					"X":	24,
					"Y":	11,
					"W":	1,
					"H":	4
				}, {
					"Id":	"WOOD_PLATFORM",
					"X":	28,
					"Y":	13,
					"W":	1,
					"H":	2
				}, {
					"Id":	"WOOD_PLATFORM",
					"X":	32,
					"Y":	12,
					"W":	1,
					"H":	3
				}, {
					"Id":	"SQUIRREL_BUSH",
					"X":	35,
					"Y":	9,
					"W":	3,
					"H":	2
				}, {
					"Id":	"WOOD_PLATFORM",
					"X":	36,
					"Y":	11,
					"W":	1,
					"H":	4
				}, {
					"Id":	"WOOD_PLATFORM",
					"X":	18,
					"Y":	6,
					"W":	1,
					"H":	5
				}, {
					"Id":	"SQUIRREL_BUSH",
					"X":	16,
					"Y":	4,
					"W":	5,
					"H":	2
				}, {
					"Id":	"SQUIRREL_BUSH",
					"X":	17,
					"Y":	3,
					"W":	3,
					"H":	1
				}, {
					"Id":	"SQUIRREL_BUSH",
					"X":	39,
					"Y":	11,
					"W":	3,
					"H":	2
				}, {
					"Id":	"WOOD_PLATFORM",
					"X":	40,
					"Y":	13,
					"W":	1,
					"H":	2
				}, {
					"Id":	"WOOD_PLATFORM",
					"X":	42,
					"Y":	10,
					"W":	1,
					"H":	5
				}, {
					"Id":	"SQUIRREL_BUSH",
					"X":	41,
					"Y":	8,
					"W":	3,
					"H":	2
				}, {
					"Id":	"PRIZE",
					"X":	6,
					"Y":	10,
					"W":	1,
					"H":	1,
					"Extra":	"ABILITY_BOMB | 128"
				}, {
					"Id":	"STRIPED_LOG_HORIZ",
					"X":	22,
					"Y":	13,
					"W":	2,
					"H":	1
				}, {
					"Id":	"SMALL_ROCK",
					"X":	15,
					"Y":	5,
					"W":	1,
					"H":	8
				}, {
					"Id":	"COIN",
					"X":	14,
					"Y":	5,
					"W":	1,
					"H":	3
				}, {
					"Id":	"STRIPED_LOG_HORIZ",
					"X":	32,
					"Y":	7,
					"W":	2,
					"H":	1
				}, {
					"Id":	"PRIZE",
					"X":	41,
					"Y":	2,
					"W":	1,
					"H":	1,
					"Extra":	"ABILITY_BOMB | 128"
				}, {
					"Id":	"COIN",
					"X":	24,
					"Y":	8,
					"W":	1,
					"H":	1
				}, {
					"Id":	"SMALL_ROCK",
					"X":	21,
					"Y":	0,
					"W":	1,
					"H":	8
				}, {
					"Id":	"CEILING_BARRIER",
					"X":	20,
					"Y":	0,
					"W":	1,
					"H":	2
				}, {
					"Id":	"COIN",
					"X":	25,
					"Y":	7,
					"W":	1,
					"H":	1
				}, {
					"Id":	"COIN",
					"X":	26,
					"Y":	6,
					"W":	1,
					"H":	1
				}, {
					"Id":	"COIN",
					"X":	27,
					"Y":	5,
					"W":	1,
					"H":	1
				}, {
					"Id":	"COIN",
					"X":	28,
					"Y":	4,
					"W":	1,
					"H":	1
				}, {
					"Id":	"SQUIRREL_BUSH",
					"X":	32,
					"Y":	3,
					"W":	5,
					"H":	2
				}, {
					"Id":	"WOOD_PLATFORM",
					"X":	34,
					"Y":	5,
					"W":	1,
					"H":	10
				}, {
					"Id":	"SQUIRREL_BUSH",
					"X":	33,
					"Y":	2,
					"W":	3,
					"H":	1
				}, {
					"Id":	"SQUIRREL_BUSH",
					"X":	37,
					"Y":	6,
					"W":	3,
					"H":	2
				}, {
					"Id":	"WOOD_PLATFORM",
					"X":	38,
					"Y":	8,
					"W":	1,
					"H":	7
				}, {
					"Id":	"STONE_BRIDGE",
					"X":	38,
					"Y":	4,
					"W":	5,
					"H":	1
				}, {
					"Id":	"BIG_HEART",
					"X":	39,
					"Y":	2,
					"W":	1,
					"H":	1
				}, {
					"Id":	"SQUIRREL_BUSH",
					"X":	44,
					"Y":	10,
					"W":	3,
					"H":	2
				}, {
					"Id":	"WOOD_PLATFORM",
					"X":	45,
					"Y":	12,
					"W":	1,
					"H":	3
				}, {
					"Id":	"WOOD_PLATFORM",
					"X":	48,
					"Y":	9,
					"W":	1,
					"H":	6
				}, {
					"Id":	"SQUIRREL_BUSH",
					"X":	47,
					"Y":	7,
					"W":	3,
					"H":	2
				}, {
					"Id":	"SQUIRREL_BUSH",
					"X":	50,
					"Y":	11,
					"W":	3,
					"H":	2
				}, {
					"Id":	"WOOD_PLATFORM",
					"X":	51,
					"Y":	13,
					"W":	1,
					"H":	2
				}, {
					"Id":	"STONE_BRIDGE",
					"X":	50,
					"Y":	10,
					"W":	3,
					"H":	1
				}, {
					"Id":	"STONE_BRIDGE",
					"X":	59,
					"Y":	10,
					"W":	3,
					"H":	1
				}, {
					"Id":	"SQUIRREL_BUSH",
					"X":	59,
					"Y":	11,
					"W":	3,
					"H":	2
				}, {
					"Id":	"WOOD_PLATFORM",
					"X":	60,
					"Y":	13,
					"W":	1,
					"H":	2
				}, {
					"Id":	"LAVA_MAIN",
					"X":	52,
					"Y":	13,
					"W":	8,
					"H":	2
				}, {
					"Id":	"LAVA_MAIN",
					"X":	61,
					"Y":	13,
					"W":	8,
					"H":	2
				}, {
					"Id":	"GROUND",
					"X":	69,
					"Y":	8,
					"W":	6,
					"H":	7
				}, {
					"Id":	"GROUND",
					"X":	75,
					"Y":	6,
					"W":	5,
					"H":	9
				}, {
					"Id":	"PALM_TREE",
					"X":	69,
					"Y":	4,
					"W":	1,
					"H":	4
				}, {
					"Id":	"PALM_TREE",
					"X":	71,
					"Y":	4,
					"W":	1,
					"H":	4
				}, {
					"Id":	"PALM_TREE",
					"X":	73,
					"Y":	4,
					"W":	1,
					"H":	4
				}, {
					"Id":	"STONE_BRIDGE",
					"X":	81,
					"Y":	11,
					"W":	14,
					"H":	1
				}, {
					"Id":	"SQUIRREL_BUSH",
					"X":	80,
					"Y":	12,
					"W":	3,
					"H":	2
				}, {
					"Id":	"SQUIRREL_BUSH",
					"X":	84,
					"Y":	13,
					"W":	3,
					"H":	2
				}, {
					"Id":	"SQUIRREL_BUSH",
					"X":	89,
					"Y":	12,
					"W":	3,
					"H":	2
				}, {
					"Id":	"SQUIRREL_BUSH",
					"X":	94,
					"Y":	13,
					"W":	3,
					"H":	2
				}, {
					"Id":	"WOOD_PLATFORM",
					"X":	81,
					"Y":	14,
					"W":	1,
					"H":	1
				}, {
					"Id":	"WOOD_PLATFORM",
					"X":	90,
					"Y":	14,
					"W":	1,
					"H":	1
				}, {
					"Id":	"SPRING",
					"X":	81,
					"Y":	9,
					"W":	1,
					"H":	1
				}, {
					"Id":	"GRAY_BRICKS",
					"X":	97,
					"Y":	2,
					"W":	14,
					"H":	13
				}, {
					"Id":	"STONE_BRIDGE",
					"X":	112,
					"Y":	4,
					"W":	5,
					"H":	1
				}, {
					"Id":	"SQUIRREL_BUSH",
					"X":	114,
					"Y":	0,
					"W":	7,
					"H":	3
				}, {
					"Id":	"WOOD_PLATFORM",
					"X":	117,
					"Y":	3,
					"W":	1,
					"H":	12
				}, {
					"Id":	"SQUIRREL_BUSH",
					"X":	122,
					"Y":	0,
					"W":	7,
					"H":	3
				}, {
					"Id":	"WOOD_PLATFORM",
					"X":	125,
					"Y":	3,
					"W":	1,
					"H":	12
				}, {
					"Id":	"SQUIRREL_BUSH",
					"X":	130,
					"Y":	1,
					"W":	2,
					"H":	2
				}, {
					"Id":	"SQUIRREL_BUSH",
					"X":	138,
					"Y":	0,
					"W":	7,
					"H":	3
				}, {
					"Id":	"WOOD_PLATFORM",
					"X":	133,
					"Y":	3,
					"W":	1,
					"H":	12
				}, {
					"Id":	"WOOD_PLATFORM",
					"X":	141,
					"Y":	3,
					"W":	1,
					"H":	12
				}, {
					"Id":	"SQUIRREL_BUSH",
					"X":	146,
					"Y":	0,
					"W":	7,
					"H":	3
				}, {
					"Id":	"WOOD_PLATFORM",
					"X":	149,
					"Y":	3,
					"W":	1,
					"H":	12
				}, {
					"Id":	"LAVA_MAIN",
					"X":	98,
					"Y":	12,
					"W":	1,
					"H":	2
				}, {
					"Id":	"LAVA_MAIN",
					"X":	100,
					"Y":	7,
					"W":	1,
					"H":	2
				}, {
					"Id":	"LAVA_MAIN",
					"X":	102,
					"Y":	12,
					"W":	1,
					"H":	2
				}, {
					"Id":	"LAVA_MAIN",
					"X":	105,
					"Y":	7,
					"W":	1,
					"H":	2
				}, {
					"Id":	"LAVA_MAIN",
					"X":	107,
					"Y":	12,
					"W":	1,
					"H":	2
				}, {
					"Id":	"LAVA_MAIN",
					"X":	109,
					"Y":	7,
					"W":	1,
					"H":	2
				}, {
					"Id":	"STONE_BRIDGE",
					"X":	119,
					"Y":	4,
					"W":	5,
					"H":	1
				}, {
					"Id":	"STONE_BRIDGE",
					"X":	127,
					"Y":	4,
					"W":	5,
					"H":	1
				}, {
					"Id":	"STRIPED_LOG_HORIZ",
					"X":	123,
					"Y":	6,
					"W":	2,
					"H":	1
				}, {
					"Id":	"STRIPED_LOG_HORIZ",
					"X":	126,
					"Y":	8,
					"W":	3,
					"H":	1
				}, {
					"Id":	"STRIPED_LOG_HORIZ",
					"X":	130,
					"Y":	10,
					"W":	3,
					"H":	1
				}, {
					"Id":	"CEILING_BARRIER",
					"X":	96,
					"Y":	0,
					"W":	1,
					"H":	5
				}, {
					"Id":	"SPIKES",
					"X":	97,
					"Y":	1,
					"W":	14,
					"H":	1
				}, {
					"Id":	"SQUIRREL_BUSH",
					"X":	112,
					"Y":	5,
					"W":	5,
					"H":	3
				}, {
					"Id":	"WOOD_PLATFORM",
					"X":	114,
					"Y":	8,
					"W":	1,
					"H":	7
				}, {
					"Id":	"SOLID_BLOCK",
					"X":	132,
					"Y":	0,
					"W":	1,
					"H":	5
				}, {
					"Id":	"SQUIRREL_BUSH",
					"X":	118,
					"Y":	7,
					"W":	5,
					"H":	3
				}, {
					"Id":	"WOOD_PLATFORM",
					"X":	120,
					"Y":	10,
					"W":	1,
					"H":	5
				}, {
					"Id":	"SQUIRREL_BUSH",
					"X":	111,
					"Y":	9,
					"W":	3,
					"H":	3
				}, {
					"Id":	"WOOD_PLATFORM",
					"X":	112,
					"Y":	12,
					"W":	1,
					"H":	3
				}, {
					"Id":	"SQUIRREL_BUSH",
					"X":	122,
					"Y":	11,
					"W":	3,
					"H":	3
				}, {
					"Id":	"WOOD_PLATFORM",
					"X":	123,
					"Y":	14,
					"W":	1,
					"H":	1
				}, {
					"Id":	"PALM_TREE",
					"X":	115,
					"Y":	11,
					"W":	1,
					"H":	4
				}, {
					"Id":	"PALM_TREE",
					"X":	118,
					"Y":	11,
					"W":	1,
					"H":	4
				}, {
					"Id":	"PALM_TREE",
					"X":	127,
					"Y":	11,
					"W":	1,
					"H":	4
				}, {
					"Id":	"LAVA_MAIN",
					"X":	130,
					"Y":	11,
					"W":	3,
					"H":	2
				}, {
					"Id":	"LAVA_MAIN",
					"X":	134,
					"Y":	11,
					"W":	3,
					"H":	2
				}, {
					"Id":	"STRIPED_LOG_HORIZ",
					"X":	138,
					"Y":	8,
					"W":	3,
					"H":	1
				}, {
					"Id":	"STRIPED_LOG_HORIZ",
					"X":	142,
					"Y":	5,
					"W":	3,
					"H":	1
				}, {
					"Id":	"STRIPED_LOG_HORIZ",
					"X":	146,
					"Y":	6,
					"W":	3,
					"H":	1
				}, {
					"Id":	"STRIPED_LOG_HORIZ",
					"X":	150,
					"Y":	7,
					"W":	3,
					"H":	1
				}, {
					"Id":	"SQUIRREL_BUSH",
					"X":	142,
					"Y":	8,
					"W":	5,
					"H":	3
				}, {
					"Id":	"WOOD_PLATFORM",
					"X":	144,
					"Y":	11,
					"W":	1,
					"H":	4
				}, {
					"Id":	"SQUIRREL_BUSH",
					"X":	150,
					"Y":	9,
					"W":	3,
					"H":	3
				}, {
					"Id":	"WOOD_PLATFORM",
					"X":	151,
					"Y":	12,
					"W":	1,
					"H":	3
				}, {
					"Id":	"SQUIRREL_BUSH",
					"X":	136,
					"Y":	4,
					"W":	3,
					"H":	3
				}, {
					"Id":	"WOOD_PLATFORM",
					"X":	137,
					"Y":	7,
					"W":	1,
					"H":	8
				}, {
					"Id":	"STRIPED_LOG_HORIZ",
					"X":	134,
					"Y":	10,
					"W":	3,
					"H":	1
				}, {
					"Id":	"BIG_HEART",
					"X":	139,
					"Y":	7,
					"W":	1,
					"H":	1
				}, {
					"Id":	"SOLID_BLOCK",
					"X":	130,
					"Y":	0,
					"W":	2,
					"H":	1
				}, {
					"Id":	"SQUIRREL_BUSH",
					"X":	133,
					"Y":	0,
					"W":	4,
					"H":	3
				}, {
					"Id":	"CEILING_BARRIER",
					"X":	129,
					"Y":	0,
					"W":	1,
					"H":	2
				}, {
					"Id":	"SQUIRREL_BUSH",
					"X":	154,
					"Y":	4,
					"W":	3,
					"H":	3
				}, {
					"Id":	"WOOD_PLATFORM",
					"X":	155,
					"Y":	7,
					"W":	1,
					"H":	8
				}, {
					"Id":	"PALM_TREE",
					"X":	139,
					"Y":	11,
					"W":	1,
					"H":	4
				}, {
					"Id":	"PALM_TREE",
					"X":	147,
					"Y":	11,
					"W":	1,
					"H":	4
				}, {
					"Id":	"PALM_TREE",
					"X":	153,
					"Y":	11,
					"W":	1,
					"H":	4
				}, {
					"Id":	"PALM_TREE",
					"X":	157,
					"Y":	11,
					"W":	1,
					"H":	4
				}, {
					"Id":	"PALM_TREE",
					"X":	25,
					"Y":	13,
					"W":	1,
					"H":	2
				}, {
					"Id":	"PALM_TREE",
					"X":	43,
					"Y":	13,
					"W":	1,
					"H":	2
				}, {
					"Id":	"PALM_TREE",
					"X":	30,
					"Y":	13,
					"W":	1,
					"H":	2
				}, {
					"Id":	"BIG_SPIKY_BUSH",
					"X":	76,
					"Y":	5,
					"W":	1,
					"H":	1
				}, {
					"Id":	"BIG_SPIKY_BUSH",
					"X":	78,
					"Y":	5,
					"W":	1,
					"H":	1
				}, {
					"Id":	"PRIZE",
					"X":	152,
					"Y":	4,
					"W":	1,
					"H":	1,
					"Extra":	"ABILITY_BOMB | 128"
				}, {
					"Id":	"SQUIRREL_BUSH",
					"X":	163,
					"Y":	11,
					"W":	3,
					"H":	3
				}, {
					"Id":	"WOOD_PLATFORM",
					"X":	164,
					"Y":	14,
					"W":	1,
					"H":	1
				}, {
					"Id":	"SQUIRREL_BUSH",
					"X":	171,
					"Y":	11,
					"W":	3,
					"H":	3
				}, {
					"Id":	"SQUIRREL_BUSH",
					"X":	167,
					"Y":	11,
					"W":	3,
					"H":	3
				}, {
					"Id":	"WOOD_PLATFORM",
					"X":	168,
					"Y":	14,
					"W":	1,
					"H":	1
				}, {
					"Id":	"WOOD_PLATFORM",
					"X":	172,
					"Y":	14,
					"W":	1,
					"H":	1
				}, {
					"Id":	"GROUND",
					"X":	176,
					"Y":	8,
					"W":	6,
					"H":	7
				}, {
					"Id":	"EXIT_DOOR",
					"X":	178,
					"Y":	6,
					"W":	1,
					"H":	1
				}, {
					"Id":	"PALM_TREE",
					"X":	176,
					"Y":	5,
					"W":	1,
					"H":	3
				}, {
					"Id":	"PALM_TREE",
					"X":	180,
					"Y":	5,
					"W":	1,
					"H":	3
				}, {
					"Id":	"COIN",
					"X":	160,
					"Y":	5,
					"W":	3,
					"H":	3
				}, {
					"Id":	"COIN",
					"X":	164,
					"Y":	2,
					"W":	3,
					"H":	3
				}, {
					"Id":	"COIN",
					"X":	170,
					"Y":	4,
					"W":	3,
					"H":	2
				}, {
					"Id":	"COIN",
					"X":	166,
					"Y":	7,
					"W":	4,
					"H":	2
				}, {
					"Id":	"GROUND",
					"X":	182,
					"Y":	0,
					"W":	10,
					"H":	15
				}]
		}, {
			"Name":	"Sprites",
			"Type":	"Sprite",
			"Tileset":	"novasp",
			"Data":	[{
					"Id":	"BOMB_POP_GENERATOR",
					"X":	30,
					"Y":	0,
					"W":	1,
					"H":	1,
					"Extra":	"1"
				}, {
					"Id":	"BOMB_GUY",
					"X":	10,
					"Y":	12,
					"W":	1,
					"H":	1,
					"XFlip":	true
				}, {
					"Id":	"CHECKPOINT",
					"X":	40,
					"Y":	3,
					"W":	1,
					"H":	1
				}, {
					"Id":	"BOMB_POP_GENERATOR",
					"X":	65,
					"Y":	0,
					"W":	1,
					"H":	1,
					"Extra":	"15"
				}, {
					"Id":	"MOVING_PLATFORM_PUSH",
					"X":	43,
					"Y":	4,
					"W":	1,
					"H":	1,
					"Extra":	"1"
				}, {
					"Id":	"TOAST",
					"X":	54,
					"Y":	13,
					"W":	1,
					"H":	1
				}, {
					"Id":	"TOAST",
					"X":	57,
					"Y":	13,
					"W":	1,
					"H":	1
				}, {
					"Id":	"BOMB_POP_GENERATOR",
					"X":	77,
					"Y":	0,
					"W":	1,
					"H":	1,
					"Extra":	"15"
				}, {
					"Id":	"TOAST",
					"X":	63,
					"Y":	13,
					"W":	1,
					"H":	1
				}, {
					"Id":	"GRILLBERT",
					"X":	76,
					"Y":	4,
					"W":	1,
					"H":	1,
					"XFlip":	true
				}, {
					"Id":	"GRILLBERT",
					"X":	73,
					"Y":	6,
					"W":	1,
					"H":	1,
					"XFlip":	true
				}, {
					"Id":	"GRILLBERT",
					"X":	70,
					"Y":	5,
					"W":	1,
					"H":	1,
					"XFlip":	true
				}, {
					"Id":	"CLOUD",
					"X":	86,
					"Y":	8,
					"W":	1,
					"H":	1,
					"XFlip":	true
				}, {
					"Id":	"CLOUD",
					"X":	89,
					"Y":	5,
					"W":	1,
					"H":	1,
					"XFlip":	true
				}, {
					"Id":	"CLOUD",
					"X":	84,
					"Y":	6,
					"W":	1,
					"H":	1,
					"XFlip":	true
				}, {
					"Id":	"CHECKPOINT",
					"X":	114,
					"Y":	3,
					"W":	1,
					"H":	1
				}, {
					"Id":	"TOAST",
					"X":	98,
					"Y":	12,
					"W":	1,
					"H":	1
				}, {
					"Id":	"TOAST",
					"X":	102,
					"Y":	12,
					"W":	1,
					"H":	1
				}, {
					"Id":	"TOAST",
					"X":	105,
					"Y":	7,
					"W":	1,
					"H":	1
				}, {
					"Id":	"TOAST",
					"X":	100,
					"Y":	7,
					"W":	1,
					"H":	1
				}, {
					"Id":	"TOAST",
					"X":	109,
					"Y":	7,
					"W":	1,
					"H":	1
				}, {
					"Id":	"TOAST",
					"X":	107,
					"Y":	12,
					"W":	1,
					"H":	1
				}, {
					"Id":	"MAMA_LUIGI",
					"X":	128,
					"Y":	3,
					"W":	1,
					"H":	1
				}, {
					"Id":	"MAMA_LUIGI",
					"X":	121,
					"Y":	3,
					"W":	1,
					"H":	1
				}, {
					"Id":	"BOMB_POP_GENERATOR",
					"X":	136,
					"Y":	0,
					"W":	1,
					"H":	1,
					"Extra":	"1"
				}, {
					"Id":	"TOAST",
					"X":	131,
					"Y":	11,
					"W":	1,
					"H":	1
				}, {
					"Id":	"TOAST",
					"X":	135,
					"Y":	11,
					"W":	1,
					"H":	1
				}, {
					"Id":	"ELECTRIC_FAN",
					"X":	143,
					"Y":	4,
					"W":	1,
					"H":	1,
					"XFlip":	true
				}, {
					"Id":	"CLOUD",
					"X":	129,
					"Y":	7,
					"W":	1,
					"H":	1,
					"XFlip":	true
				}, {
					"Id":	"CLOUD",
					"X":	132,
					"Y":	6,
					"W":	1,
					"H":	1,
					"XFlip":	true
				}, {
					"Id":	"CHECKPOINT",
					"X":	151,
					"Y":	6,
					"W":	1,
					"H":	1
				}, {
					"Id":	"MOVING_PLATFORM_PUSH",
					"X":	148,
					"Y":	10,
					"W":	1,
					"H":	1
				}, {
					"Id":	"COLLECTIBLE",
					"X":	165,
					"Y":	3,
					"W":	1,
					"H":	1
				}]
		}, {
			"Name":	"Control",
			"Type":	"Control",
			"Tileset":	"novact",
			"Data":	[{
					"Id":	"PLAYER_START_R",
					"X":	3,
					"Y":	12,
					"W":	1,
					"H":	1
				}, {
					"Id":	"BACKGROUND",
					"X":	0,
					"Y":	0,
					"W":	1,
					"H":	1,
					"Extra":	"CLOUDS"
				}, {
					"Id":	"SCROLL_LOCK",
					"X":	191,
					"Y":	0,
					"W":	1,
					"H":	1
				}]
		}]
}